{
    "nodeid": "process_lookup_web_annif",
    "type": "process",
    "subtype": "lookups",
    "subsubtype": "web",
    "title": "Annif lookup",
    "status": "usable",
    "tags":["library", "finna"],
    "usage":"",
    "description": "Get subjec suggestions from Annif (FINNA-based)",
    
    "scripts": {
        "hello": "out.say('news', 'You added a commons checker node'); ",
        "bye": "out.say('finish', 'Bye!'); ",
        
        "init": 
        [
			"context.vars.success_counter = 0; "

		],
		
		"pre_run": "out.value = context.doc[context.node.params.in_field];" ,
		
         "finish":"out.say('finish', 'Done!'); "
    },
    
    "views": {
    
    }
  
}
